cookiecutter_hypermodern_python_instance/__init__.py
cookiecutter_hypermodern_python_instance/__main__.py
cookiecutter_hypermodern_python_instance/py.typed
cookiecutter_hypermodern_python_instance-2022.6.3.dist-info/entry_points.txt
cookiecutter_hypermodern_python_instance-2022.6.3.dist-info/LICENSE
cookiecutter_hypermodern_python_instance-2022.6.3.dist-info/WHEEL
cookiecutter_hypermodern_python_instance-2022.6.3.dist-info/METADATA
cookiecutter_hypermodern_python_instance-2022.6.3.dist-info/RECORD
