Metadata-Version: 2.1
Name: cookiecutter-hypermodern-python-instance
Version: 2022.6.3
Summary: Cookiecutter Hypermodern Python Instance
Home-page: https://github.com/cjolowicz/cookiecutter-hypermodern-python-instance
License: MIT
Author: Claudio Jolowicz
Author-email: mail@claudiojolowicz.com
Requires-Python: >=3.7,<4.0
Classifier: Development Status :: 1 - Planning
Classifier: License :: OSI Approved :: MIT License
Classifier: Programming Language :: Python :: 3
Classifier: Programming Language :: Python :: 3.10
Classifier: Programming Language :: Python :: 3.7
Classifier: Programming Language :: Python :: 3.8
Classifier: Programming Language :: Python :: 3.9
Requires-Dist: click (>=8.0.1)
Project-URL: Changelog, https://github.com/cjolowicz/cookiecutter-hypermodern-python-instance/releases
Project-URL: Documentation, https://cookiecutter-hypermodern-python-instance.readthedocs.io
Project-URL: Repository, https://github.com/cjolowicz/cookiecutter-hypermodern-python-instance
